[
    {
        "Id"            : 1,
        "Name"          : "死亡缠绕",
        "Level"         : 0,
        "Type"          : 1,
        "Desc"          : "以自身生命为祭，通过死亡缠绕伤害/治疗一个敌方/友方单位。\n\n等级 1 - 以自身75点生命的代价，伤害/治疗一个敌方/友方单位100点的生命。\n等级 2 - 以自身100点生命的代价，伤害/治疗一个敌方/友方单位150点的生命。\n等级 3 - 以自身125点生命的代价，伤害/治疗一个敌方/友方单位200点的生命。\n等级 4 - 以自身150点生命的代价，伤害/治疗一个敌方/友方单位250点的生命。"
    },
    {
        "Id"            : 2,
        "Name"          : "无光之盾",
        "Level"         : 0,
        "Type"          : 1,
        "Desc"          : "用黑暗能量创造一个盾牌来保护友方的单位，在盾牌消失前吸收一定量的伤害。在盾牌被摧毁或持续时间到后，会给周围500范围内的敌方单位造成伤害。施放时移除目标身上的负面魔法效果。\n\n等级 1 - 总共能吸收110点的伤害。\n等级 2 - 总共能吸收140点的伤害。\n等级 3 - 总共能吸收170点的伤害。\n等级 4 - 总共能吸收200点的伤害。"
    },
    {
        "Id"            : 3,
        "Name"          : "霜之哀伤",
        "Level"         : 0,
        "Type"          : 2,
        "Desc"          : "地狱领主使用传说之剑霜之哀伤的极寒力量使目标减速，持续2.5秒。任何攻击被减速目标的单位得到速度的提升，持续4.5秒\n\n等级 1 - 降低目标5%/5%攻击/移动速度，提升攻击者10%/15%攻击/移动速度。\n等级 2 - 降低目标10%/10%攻击/移动速度，提升攻击者20%/15%攻击/移动速度。\n等级 3 - 降低目标15%/15%攻击/移动速度，提升攻击者30%/15%攻击/移动速度。\n等级 4 - 降低目标20%/20%攻击/移动速度，提升攻击者40%/15%攻击/移动速度。"
    },
    {
        "Id"            : 4,
        "Name"          : "回光返照",
        "Level"         : 0,
        "Type"          : 1,
        "Desc"          : "启动时，移除身上负面的魔法效果，期间所有受到的伤害转而治疗你。如果你当前的生命值低于400而技能不在CD过程中，则技能会自动启动。\n\n等级 1 - 持续4秒。\n等级 2 - 持续5秒。\n等级 3 - 持续6秒。"
    },
    {
        "Id"            : 6,
        "Name"          : "魔法箭",
        "Level"         : 0,
        "Type"          : 1,
        "Desc"          : "向一个敌方单位射出魔法箭，眩晕并造成伤害。\n\n等级1:造成100点的伤害，晕眩1.45秒。 施法间隔:10秒 施法消耗:110点魔法\n等级2:造成175点的伤害，晕眩1.55秒。 施法间隔:10秒 施法消耗:120点魔法\n等级3:造成250点的伤害，晕眩1.65秒。 施法间隔:10秒 施法消耗:130点魔法\n等级4:造成325点的伤害，晕眩1.75秒。 施法间隔:10秒 施法消耗:140点魔法"
    },
    {
        "Id"            : 7,
        "Name"          : "恐怖波动",
        "Level"         : 0,
        "Type"          : 1,
        "Desc"          : "复仇之魂放出邪恶的嚎叫，削弱敌人的护甲并打开经过路径的视野。\n\n等级1 - 减少2点的护甲并造成30点伤害。\n等级2 - 减少3点的护甲并造成50点伤害。\n等级3 - 减少4点的护甲并造成70点伤害。\n等级4 - 减少5点的护甲并造成90点伤害。"
    },
    {
        "Id"            : 8,
        "Name"          : "复仇光环",
        "Level"         : 0,
        "Type"          : 2,
        "Desc"          : "复仇之魂的存在提高了附近友方单位的物理攻击力。\n\n等级 1 - 增加12%的基础攻击力。\n等级 2 - 增加20%的基础攻击力。\n等级 3 - 增加28%的基础攻击力。\n等级 4 - 增加36%的基础攻击力。"
    },
    {
        "Id"            : 9,
        "Name"          : "移形换位",
        "Level"         : 0,
        "Type"          : 1,
        "Desc"          : "与一个目标英雄瞬间交换位置，无论敌我。移形换位打断目标的持续施法。 可用神杖升级。 如果你将目标移形换位到一个不可到达的区域，该目标将拥有5秒无视地形的能力 神杖效果：使大招CD时间由45秒变为10秒\n\n等级 1 - 施法距离700。\n等级 2 - 施法距离950。\n等级 3 - 施法距离1200。"
    }
]